PyQtInspect/__init__.py
PyQtInspect/__main__.py
PyQtInspect/pqi.py
PyQtInspect/pqi_server_gui.py
PyQtInspect/version.py
PyQtInspect/_pqi_bundle/__init__.py
PyQtInspect/_pqi_bundle/_pqi_test_utils.py
PyQtInspect/_pqi_bundle/pqi_comm.py
PyQtInspect/_pqi_bundle/pqi_comm_constants.py
PyQtInspect/_pqi_bundle/pqi_command_line_handling.py
PyQtInspect/_pqi_bundle/pqi_connect_tools.py
PyQtInspect/_pqi_bundle/pqi_contants.py
PyQtInspect/_pqi_bundle/pqi_import_hook.py
PyQtInspect/_pqi_bundle/pqi_keyboard_hook_win.py
PyQtInspect/_pqi_bundle/pqi_monkey.py
PyQtInspect/_pqi_bundle/pqi_monkey_qt.py
PyQtInspect/_pqi_bundle/pqi_monkey_qt_helpers.py
PyQtInspect/_pqi_bundle/pqi_monkey_qt_props.py
PyQtInspect/_pqi_bundle/pqi_override.py
PyQtInspect/_pqi_bundle/pqi_path_helper.py
PyQtInspect/_pqi_bundle/pqi_qt_tools.py
PyQtInspect/_pqi_bundle/pqi_stack_tools.py
PyQtInspect/_pqi_bundle/pqi_structures.py
PyQtInspect/_pqi_bundle/pqi_typing.py
PyQtInspect/_pqi_bundle/pqi_log/__init__.py
PyQtInspect/_pqi_bundle/pqi_log/_client.py
PyQtInspect/_pqi_bundle/pqi_log/_server.py
PyQtInspect/_pqi_bundle/pqi_log/base_logger.py
PyQtInspect/_pqi_bundle/pqi_log/log_utils.py
PyQtInspect/_pqi_bundle/pqi_qt_widget_props_fetcher/__init__.py
PyQtInspect/_pqi_bundle/pqi_qt_widget_props_fetcher/_fetcher.py
PyQtInspect/_pqi_bundle/pqi_qt_widget_props_fetcher/_types_repr/__init__.py
PyQtInspect/_pqi_bundle/pqi_qt_widget_props_fetcher/_types_repr/_base.py
PyQtInspect/_pqi_bundle/pqi_qt_widget_props_fetcher/_types_repr/_enum_reprs.py
PyQtInspect/_pqi_bundle/pqi_qt_widget_props_fetcher/_types_repr/_flag_reprs.py
PyQtInspect/_pqi_bundle/pqi_qt_widget_props_fetcher/_types_repr/_ordinary_types_reprs.py
PyQtInspect/_pqi_common/__init__.py
PyQtInspect/_pqi_common/pqi_setup_holder.py
PyQtInspect/_pqi_compile/compile_pqi.py
PyQtInspect/_pqi_imps/__init__.py
PyQtInspect/_pqi_imps/_pqi_execfile.py
PyQtInspect/_pqi_imps/_pqi_saved_modules.py
PyQtInspect/pqi_attach/README.txt
PyQtInspect/pqi_attach/_always_live_program.py
pyqtinspect-0.5.0.dist-info/licenses/LICENSE
pyqtinspect-0.5.0.dist-info/METADATA
pyqtinspect-0.5.0.dist-info/WHEEL
pyqtinspect-0.5.0.dist-info/entry_points.txt
pyqtinspect-0.5.0.dist-info/top_level.txt
pyqtinspect-0.5.0.dist-info/RECORD
