Metadata-Version: 2.4
Name: PyQtInspect
Version: 0.5.0
Summary: To inspect PyQt/PySide program elements like Chrome's element inspector
Home-page: https://jeza-chen.com/PyqtInspect
Author: Jianzhang Chen
Author-email: jezachen@163.com
License: EPL-2.0
Keywords: pyqt pyside inspect
Classifier: Programming Language :: Python :: 3.7
Classifier: Programming Language :: Python :: 3.8
Classifier: Programming Language :: Python :: 3.9
Classifier: Programming Language :: Python :: 3.10
Classifier: Programming Language :: Python :: 3.11
Classifier: Programming Language :: Python :: 3.12
Classifier: Programming Language :: Python :: 3.13
Classifier: Development Status :: 4 - Beta
Classifier: License :: OSI Approved :: Eclipse Public License 2.0 (EPL-2.0)
Requires-Python: >=3.7, <4
License-File: LICENSE
Requires-Dist: psutil
Requires-Dist: PyQt5
Requires-Dist: wingrab; platform_system == "Windows"
Requires-Dist: pyobjc-framework-Cocoa; platform_system == "Darwin"
Requires-Dist: ihook
Dynamic: author
Dynamic: author-email
Dynamic: classifier
Dynamic: description
Dynamic: description-content-type
Dynamic: home-page
Dynamic: keywords
Dynamic: license
Dynamic: license-file
Dynamic: requires-dist
Dynamic: requires-python
Dynamic: summary
